pdf2pptx/169.pptx
pdf2pptx/43.pptx
pdf2pptx/__init__.py
pdf2pptx/__main__.py
pdf2pptx/convertor.py
pdf2pptx/version
pdf2pptx_cli-0.1.2.dist-info/LICENSE
pdf2pptx_cli-0.1.2.dist-info/METADATA
pdf2pptx_cli-0.1.2.dist-info/WHEEL
pdf2pptx_cli-0.1.2.dist-info/entry_points.txt
pdf2pptx_cli-0.1.2.dist-info/top_level.txt
pdf2pptx_cli-0.1.2.dist-info/RECORD
