Metadata-Version: 2.1
Name: pdf2pptx-cli
Version: 0.1.2
Summary: convert pdf to 1200 dpi image ppt
Home-page: https://github.com/chunibyo-wly/pdf2pptx
Author: chunibyo-wly
Author-email: chunibyo.wly@gmail.com
License: MIT
Platform: UNKNOWN
Classifier: Development Status :: 4 - Beta
Classifier: License :: OSI Approved :: MIT License
Classifier: Programming Language :: Python :: 3
Classifier: Operating System :: Unix
Classifier: Operating System :: MacOS :: MacOS X
Classifier: Operating System :: Microsoft :: Windows
Requires-Dist: pillow (>=8.2.0)
Requires-Dist: pdf2image (>=1.15.1)
Requires-Dist: python-pptx (>=0.6.19)
